MANIFEST.in
README.md
pyproject.toml
setup.py
riso_sdk.egg-info/PKG-INFO
riso_sdk.egg-info/SOURCES.txt
riso_sdk.egg-info/dependency_links.txt
riso_sdk.egg-info/requires.txt
riso_sdk.egg-info/top_level.txt
sdk/__init__.py
sdk/apps.py
sdk/utils.py
sdk/allauth/__init__.py
sdk/allauth/adapters.py
sdk/allauth/context_processors.py
sdk/allauth/forms.py
sdk/contrib/__init__.py
sdk/contrib/admin/__init__.py
sdk/contrib/admin/options.py
sdk/contrib/messages/__init__.py
sdk/contrib/messages/templatetags/__init__.py
sdk/contrib/messages/templatetags/sweet_message.py
sdk/db/__init__.py
sdk/db/models/__init__.py
sdk/db/models/base.py
sdk/sso/__init__.py
sdk/sso/client/__init__.py
sdk/sso/client/apps.py
sdk/sso/client/client.py
sdk/sso/client/settings.py
sdk/sso/server/__init__.py
sdk/sso/server/apps.py
sdk/sso/server/models.py
sdk/sso/server/server.py
sdk/sso/server/migrations/0001_initial.py
sdk/sso/server/migrations/__init__.py
sdk/sso/webservices/__init__.py
sdk/sso/webservices/exceptions.py
sdk/sso/webservices/models.py
sdk/sso/webservices/sync.py
sdk/static/.DS_Store
sdk/static/jquery/jquery.min.js
sdk/static/saul/.DS_Store
sdk/static/saul/css/style.bundle.css
sdk/static/saul/js/.DS_Store
sdk/static/saul/js/scripts.bundle.js
sdk/static/saul/js/widgets.bundle.js
sdk/static/saul/media/.DS_Store
sdk/static/saul/media/avatars/300-1.jpg
sdk/static/saul/media/avatars/300-10.jpg
sdk/static/saul/media/avatars/300-11.jpg
sdk/static/saul/media/avatars/300-12.jpg
sdk/static/saul/media/avatars/300-13.jpg
sdk/static/saul/media/avatars/300-14.jpg
sdk/static/saul/media/avatars/300-15.jpg
sdk/static/saul/media/avatars/300-16.jpg
sdk/static/saul/media/avatars/300-17.jpg
sdk/static/saul/media/avatars/300-18.jpg
sdk/static/saul/media/avatars/300-19.jpg
sdk/static/saul/media/avatars/300-2.jpg
sdk/static/saul/media/avatars/300-20.jpg
sdk/static/saul/media/avatars/300-21.jpg
sdk/static/saul/media/avatars/300-22.jpg
sdk/static/saul/media/avatars/300-23.jpg
sdk/static/saul/media/avatars/300-24.jpg
sdk/static/saul/media/avatars/300-25.jpg
sdk/static/saul/media/avatars/300-26.jpg
sdk/static/saul/media/avatars/300-27.jpg
